klcreqs/__init__.py
klcreqs/constants.py
klcreqs/core.py
klcreqs-2023.2.17.dist-info/METADATA
klcreqs-2023.2.17.dist-info/WHEEL
klcreqs-2023.2.17.dist-info/top_level.txt
klcreqs-2023.2.17.dist-info/RECORD
