Metadata-Version: 2.1
Name: klcreqs
Version: 2023.2.17
Summary: library for streamlining api requests
Home-page: UNKNOWN
Author: Thomas Nemechek
Author-email: tnemechek@klcapital.com
License: UNKNOWN
Platform: UNKNOWN
Classifier: Programming Language :: Python
Requires-Dist: numpy (>=1.20.3)
Requires-Dist: pandas (>=1.4.3)
Requires-Dist: requests (>=2.26.0)
